portalbrasil/__init__.py
portalbrasil/legislativo/__init__.py
portalbrasil/legislativo/configure.zcml
portalbrasil/legislativo/dependencies.zcml
portalbrasil/legislativo/distributions.zcml
portalbrasil/legislativo/handlers.py
portalbrasil/legislativo/interfaces.py
portalbrasil/legislativo/permissions.zcml
portalbrasil/legislativo/profiles.zcml
portalbrasil/legislativo/testing.py
portalbrasil/legislativo/content/__init__.py
portalbrasil/legislativo/controlpanel/__init__.py
portalbrasil/legislativo/controlpanel/configure.zcml
portalbrasil/legislativo/distributions/legislativo/image.png
portalbrasil/legislativo/distributions/legislativo/profiles.json
portalbrasil/legislativo/distributions/legislativo/schema.json
portalbrasil/legislativo/distributions/legislativo/content/.gitignore
portalbrasil/legislativo/distributions/legislativo/content/.gitkeep
portalbrasil/legislativo/distributions/legislativo/content/discussions.json
portalbrasil/legislativo/distributions/legislativo/content/portlets.json
portalbrasil/legislativo/distributions/legislativo/content/principals.json
portalbrasil/legislativo/distributions/legislativo/content/redirects.json
portalbrasil/legislativo/distributions/legislativo/content/relations.json
portalbrasil/legislativo/distributions/legislativo/content/translations.json
portalbrasil/legislativo/distributions/legislativo/content/content/__metadata__.json
portalbrasil/legislativo/distributions/legislativo/content/content/00cfedfb28a3447ba6693562774f0ef7/data.json
portalbrasil/legislativo/distributions/legislativo/content/content/0724a67fa1364951b9be9c477802f20d/data.json
portalbrasil/legislativo/distributions/legislativo/content/content/3cfe6f015e054e8cbac486bcc12d5e16/data.json
portalbrasil/legislativo/distributions/legislativo/content/content/3cfe6f015e054e8cbac486bcc12d5e16/image/foto-senado.jpeg
portalbrasil/legislativo/distributions/legislativo/content/content/4442dfb4d5254595b7b7f28f83268db6/data.json
portalbrasil_legislativo-4.0.0a3.dist-info/METADATA
portalbrasil_legislativo-4.0.0a3.dist-info/WHEEL
portalbrasil_legislativo-4.0.0a3.dist-info/entry_points.txt
portalbrasil_legislativo-4.0.0a3.dist-info/licenses/LICENSE.GPL
portalbrasil_legislativo-4.0.0a3.dist-info/licenses/LICENSE.md
portalbrasil_legislativo-4.0.0a3.dist-info/RECORD
